CSVLib/__init__.py
robotframework_csvlib-1.0.2.dist-info/LICENSE
robotframework_csvlib-1.0.2.dist-info/METADATA
robotframework_csvlib-1.0.2.dist-info/WHEEL
robotframework_csvlib-1.0.2.dist-info/top_level.txt
robotframework_csvlib-1.0.2.dist-info/RECORD
