Metadata-Version: 2.1
Name: robotframework-csvlib
Version: 1.0.2
Summary: CSV library for robotframework written in Python 3
Home-page: https://github.com/Zeroune/robotframework-csvlib
Author: Zeroune
License: UNKNOWN
Platform: UNKNOWN
Classifier: Programming Language :: Python :: 3
Classifier: License :: OSI Approved :: MIT License
